main/__init__.py
main/__main__.py
main/config.json
main/server.py
mcp_melotts-1.0.0.dist-info/METADATA
mcp_melotts-1.0.0.dist-info/WHEEL
mcp_melotts-1.0.0.dist-info/entry_points.txt
mcp_melotts-1.0.0.dist-info/licenses/LICENSE
mcp_melotts-1.0.0.dist-info/RECORD
